[{"__type__":"cc.SpriteFrame","content":{"name":"slot-2-bonus-item-5","texture":"99xzcgns1ONbMgitgqsCQS","rect":[214,0,106,93],"offset":[0,0],"originalSize":[106,93],"capInsets":[0,0,0,0]}},{"__type__":"cc.SpriteFrame","content":{"name":"slot-2-bonus-item-6","texture":"99xzcgns1ONbMgitgqsCQS","rect":[107,384,106,93],"offset":[0,0],"originalSize":[106,93],"capInsets":[0,0,0,0]}},{"__type__":"cc.SpriteFrame","content":{"name":"slot-2-item-4","texture":"99xzcgns1ONbMgitgqsCQS","rect":[0,294,106,97],"offset":[0,0],"originalSize":[106,97],"capInsets":[0,0,0,0]}},{"__type__":"cc.SpriteFrame","content":{"name":"slot-2-bonus-item-7","texture":"99xzcgns1ONbMgitgqsCQS","rect":[107,290,106,93],"offset":[0,0],"originalSize":[106,93],"capInsets":[0,0,0,0]}},{"__type__":"cc.SpriteFrame","content":{"name":"slot-2-bonus-item-3","texture":"99xzcgns1ONbMgitgqsCQS","rect":[214,188,106,93],"offset":[0,0],"originalSize":[106,93],"capInsets":[0,0,0,0]}},{"__type__":"cc.SpriteFrame","content":{"name":"slot-2-bonus-item-1","texture":"99xzcgns1ONbMgitgqsCQS","rect":[107,196,106,93],"offset":[0,0],"originalSize":[106,93],"capInsets":[0,0,0,0]}},{"__type__":"cc.SpriteFrame","content":{"name":"slot-2-bonus-item-2","texture":"99xzcgns1ONbMgitgqsCQS","rect":[214,282,106,93],"offset":[0,0],"originalSize":[106,93],"capInsets":[0,0,0,0]}},{"__type__":"cc.SpriteFrame","content":{"name":"slot-2-item-3","texture":"99xzcgns1ONbMgitgqsCQS","rect":[0,392,106,97],"offset":[0,0],"originalSize":[106,97],"capInsets":[0,0,0,0]}},{"__type__":"cc.SpriteFrame","content":{"name":"slot-2-item-2","texture":"99xzcgns1ONbMgitgqsCQS","rect":[107,0,106,97],"offset":[0,0],"originalSize":[106,97],"capInsets":[0,0,0,0]}},{"__type__":"cc.SpriteFrame","content":{"name":"slot-2-item-7","texture":"99xzcgns1ONbMgitgqsCQS","rect":[0,0,106,97],"offset":[0,0],"originalSize":[106,97],"capInsets":[0,0,0,0]}},{"__type__":"cc.SpriteFrame","content":{"name":"slot-2-bonus-item-8","texture":"99xzcgns1ONbMgitgqsCQS","rect":[214,376,106,93],"offset":[0,0],"originalSize":[106,93],"capInsets":[0,0,0,0]}},{"__type__":"cc.SpriteFrame","content":{"name":"slot-2-item-6","texture":"99xzcgns1ONbMgitgqsCQS","rect":[0,98,106,97],"offset":[0,0],"originalSize":[106,97],"capInsets":[0,0,0,0]}},{"__type__":"cc.SpriteFrame","content":{"name":"slot-2-item-1","texture":"99xzcgns1ONbMgitgqsCQS","rect":[107,98,106,97],"offset":[0,0],"originalSize":[106,97],"capInsets":[0,0,0,0]}},{"__type__":"cc.SpriteFrame","content":{"name":"slot-2-bonus-item-4","texture":"99xzcgns1ONbMgitgqsCQS","rect":[214,94,106,93],"offset":[0,0],"originalSize":[106,93],"capInsets":[0,0,0,0]}},{"__type__":"cc.SpriteFrame","content":{"name":"slot-2-item-5","texture":"99xzcgns1ONbMgitgqsCQS","rect":[0,196,106,97],"offset":[0,0],"originalSize":[106,97],"capInsets":[0,0,0,0]}}]