[{"__type__":"cc.Prefab","_name":"chan-le-history-item-2-node","data":{"__id__":1}},{"__type__":"cc.Node","_name":"chan-le-history-item-2-node","_children":[{"__id__":2},{"__id__":4},{"__id__":6}],"_level":1,"_components":[{"__type__":"01815XhQjdEMps93FKp4Yy7","node":{"__id__":1},"chanLabel":{"__id__":5},"leLabel":{"__id__":7},"bgSprite":{"__id__":3},"chanSpriteFrame":{"__uuid__":"20bPkFVkVBy7AFSBUvZOGp"},"leSpriteFrame":{"__uuid__":"1bVPFJFn1FbohNHgjL0HhC"}}],"_prefab":{"__type__":"cc.PrefabInfo","root":{"__id__":1},"asset":{"__uuid__":"4dVMAQSHNPxJchUdesINXz"},"fileId":"fbgQmcwIZGbbzELh5hPg2O"},"_contentSize":{"__type__":"cc.Size","width":25,"height":24}},{"__type__":"cc.Node","_name":"bg-sprite","_parent":{"__id__":1},"_components":[{"__id__":3}],"_prefab":{"__type__":"cc.PrefabInfo","root":{"__id__":1},"asset":{"__uuid__":"4dVMAQSHNPxJchUdesINXz"},"fileId":"813TcbpdtNF5QRR6D2uyso"},"_contentSize":{"__type__":"cc.Size","width":24,"height":25},"_position":{"__type__":"cc.Vec3","x":1}},{"__type__":"cc.Sprite","node":{"__id__":2},"_materials":[{"__uuid__":"ecpdLyjvZBwrvm+cedCcQy"}],"_spriteFrame":{"__uuid__":"20bPkFVkVBy7AFSBUvZOGp"},"_sizeMode":0},{"__type__":"cc.Node","_name":"score-chan-label","_parent":{"__id__":1},"_components":[{"__id__":5}],"_prefab":{"__type__":"cc.PrefabInfo","root":{"__id__":1},"asset":{"__uuid__":"4dVMAQSHNPxJchUdesINXz"},"fileId":"c0L+oIgX1KCKN5jQ7xxm7L"},"_contentSize":{"__type__":"cc.Size","width":16.88,"height":15},"_position":{"__type__":"cc.Vec3","x":-0.5}},{"__type__":"cc.Label","node":{"__id__":4},"_materials":[{"__uuid__":"ecpdLyjvZBwrvm+cedCcQy"}],"_useOriginalSize":false,"_string":"15","_N$string":"15","_fontSize":15,"_N$file":{"__uuid__":"1c7FFS5clGcY9rs79Iphys"},"_isSystemFontUsed":false,"_N$horizontalAlign":1,"_N$verticalAlign":1},{"__type__":"cc.Node","_name":"score-le-label","_parent":{"__id__":1},"_components":[{"__id__":7}],"_prefab":{"__type__":"cc.PrefabInfo","root":{"__id__":1},"asset":{"__uuid__":"4dVMAQSHNPxJchUdesINXz"},"fileId":"3byuwJFWZGIJqoq6Iwssnk"},"_contentSize":{"__type__":"cc.Size","width":16.88,"height":15},"_position":{"__type__":"cc.Vec3","x":-0.5,"y":0.45}},{"__type__":"cc.Label","node":{"__id__":6},"_materials":[{"__uuid__":"ecpdLyjvZBwrvm+cedCcQy"}],"_useOriginalSize":false,"_string":"15","_N$string":"15","_fontSize":15,"_N$file":{"__uuid__":"1c7FFS5clGcY9rs79Iphys"},"_isSystemFontUsed":false,"_N$horizontalAlign":1,"_N$verticalAlign":1}]